voicevox/__init__.py
voicevox/app_voicevox.py
voicevox/config.py
voicevox_provider-0.1.3.dist-info/METADATA
voicevox_provider-0.1.3.dist-info/WHEEL
voicevox_provider-0.1.3.dist-info/top_level.txt
voicevox_provider-0.1.3.dist-info/RECORD
