Metadata-Version: 2.4
Name: voicevox-provider
Version: 0.1.3
Requires-Python: >=3.12
Requires-Dist: requests>=2.32.5
Requires-Dist: aiohttp>=3.12.15
Requires-Dist: typing-extensions>=4.15.0
